marvelpy/__init__.py
marvelpy/_version.py
marvelpy/client.py
marvelpy/hello.py
marvelpy/utils/__init__.py
marvelpy/utils/auth.py
marvelpy-0.2.1.dist-info/METADATA
marvelpy-0.2.1.dist-info/WHEEL
marvelpy-0.2.1.dist-info/entry_points.txt
marvelpy-0.2.1.dist-info/top_level.txt
marvelpy-0.2.1.dist-info/RECORD
