Metadata-Version: 2.4
Name: marvelpy
Version: 0.2.1
Summary: A fully-typed Python client for the Marvel Comics API.
Author-email: Jeff Granof <jlgranof@icloud.com>
Maintainer-email: Jeff Granof <jlgranof@icloud.com>
License: MIT
Project-URL: Homepage, https://github.com/jlgranof/marvelpy
Project-URL: Documentation, https://jlgranof.github.io/marvelpy/
Project-URL: Issue Tracker, https://github.com/jlgranof/marvelpy/issues
Keywords: marvel,api,comics,client,async,typed
Classifier: Development Status :: 5 - Production/Stable
Classifier: Intended Audience :: Developers
Classifier: Operating System :: OS Independent
Classifier: Programming Language :: Python :: 3
Classifier: Programming Language :: Python :: 3.8
Classifier: Programming Language :: Python :: 3.9
Classifier: Programming Language :: Python :: 3.10
Classifier: Programming Language :: Python :: 3.11
Classifier: Programming Language :: Python :: 3.12
Classifier: Topic :: Software Development :: Libraries :: Python Modules
Classifier: Topic :: Internet :: WWW/HTTP :: Dynamic Content
Classifier: Typing :: Typed
Requires-Python: >=3.8
Requires-Dist: httpx>=0.23.0
Requires-Dist: pydantic>=1.10.0
Requires-Dist: typing-extensions>=4.9.0
Requires-Dist: click>=8.1.0
Provides-Extra: dev
Requires-Dist: pytest>=7.0.0; extra == "dev"
Requires-Dist: pytest-asyncio>=0.21.0; extra == "dev"
Requires-Dist: pytest-cov>=4.0.0; extra == "dev"
Requires-Dist: pytest-mock>=3.10.0; extra == "dev"
Requires-Dist: respx>=0.20.0; extra == "dev"
Requires-Dist: ruff>=0.1.0; extra == "dev"
Requires-Dist: mypy>=1.0.0; extra == "dev"
Requires-Dist: pre-commit>=3.0.0; extra == "dev"
Requires-Dist: mkdocs-material>=9.0.0; extra == "dev"
Requires-Dist: mkdocs-gen-files>=0.5.0; extra == "dev"
Requires-Dist: mkdocs-literate-nav>=0.6.0; extra == "dev"
Requires-Dist: mkdocs-section-index>=0.3.0; extra == "dev"
Requires-Dist: mkdocstrings[python]>=0.20.0; extra == "dev"
Requires-Dist: black>=23.0.0; extra == "dev"
Requires-Dist: isort>=5.12.0; extra == "dev"
Requires-Dist: httpx>=0.23.0; extra == "dev"
Requires-Dist: pydantic>=1.10.0; extra == "dev"
Requires-Dist: python-dotenv>=1.0.0; extra == "dev"
Provides-Extra: test
Requires-Dist: pytest>=7.0.0; extra == "test"
Requires-Dist: pytest-asyncio>=0.21.0; extra == "test"
Requires-Dist: pytest-cov>=4.0.0; extra == "test"
Requires-Dist: pytest-mock>=3.10.0; extra == "test"
Requires-Dist: respx>=0.20.0; extra == "test"
Provides-Extra: docs
Requires-Dist: mkdocs-material>=9.0.0; extra == "docs"
Requires-Dist: mkdocs-gen-files>=0.5.0; extra == "docs"
Requires-Dist: mkdocs-literate-nav>=0.6.0; extra == "docs"
Requires-Dist: mkdocs-section-index>=0.3.0; extra == "docs"
Requires-Dist: mkdocstrings[python]>=0.20.0; extra == "docs"
Requires-Dist: mike>=1.1.0; extra == "docs"
